{"runs": [{"o_u": "0.01", "ovr": "0.1", "bat": "301236", "r_t": "0", "bowl": "56007", "r": "0", "comm": "on a length, middle and length, defended to mid-on", "x": "140", "y": "209", "o_a": "0.1", "z": "5"}, {"o_u": "0.02", "ovr": "0.2", "bat": "301236", "r_t": "0", "bowl": "56007", "r": "0", "comm": "similar delivery, just short of a length, around middle and leg, Thirimanne closes the face, is beaten and hit on the pad", "x": "0", "y": "0", "o_a": "0.2", "z": "0"}, {"o_u": "0.03", "ovr": "0.3", "bat": "301236", "r_t": "0", "bowl": "56007", "r": "0", "comm": "a length ball angled across him. Pitches off and goes with the angle. Thirimanne wafts at it, and is beaten", "x": "0", "y": "0", "o_a": "0.3", "z": "0"}, {"o_u": "0.04", "ovr": "0.4", "bat": "301236", "r_t": "0", "bowl": "56007", "r": "0", "comm": "<b>dropped him</b>. A dream start ruined. Easy catch from Bijoy at first slip. He has another waft at a wide length ball, and this time gets the edge. Bijoy is wide at first slip, it has come straight down his lap, at a comfortable waist height. Just doesn't see it all the way in. Has three grabs at it, but grasses it", "x": "201", "y": "108", "o_a": "0.4", "z": "1"}, {"o_u": "0.05", "ovr": "0.5", "bat": "301236", "r_t": "1", "bowl": "56007", "r": "1", "comm": "runs this off the outside half of the bat, gets a single to third man", "x": "301", "y": "90", "o_a": "0.5", "z": "2"}, {"o_u": "0.06", "ovr": "0.6", "bat": "48472", "r_t": "0", "bowl": "56007", "r": "0", "comm": "short of a length, on the stumps, defended back to him", "x": "149", "y": "198", "o_a": "0.6", "z": "5"}, {"o_u": "1.01", "ovr": "1.1", "bat": "301236", "r_t": "1", "bowl": "300619", "r": "0", "comm": "starts outside leg, holds its line, called a wide", "x": "0", "y": "0", "o_a": "1.1", "z": "0"}, {"o_u": "1.02", "ovr": "1.1", "bat": "301236", "r_t": "0", "bowl": "300619", "r": "0", "comm": "swing for Rubel, but this starts middle and leg, and even though it has beaten the inside edge the ball is headed down leg", "x": "141", "y": "174", "o_a": "1.1", "z": "6"}, {"o_u": "1.03", "ovr": "1.2", "bat": "301236", "r_t": "1", "bowl": "300619", "r": "0", "comm": "massive wide down the leg side, Mushfiq does well to collect it", "x": "0", "y": "0", "o_a": "1.2", "z": "0"}, {"o_u": "1.04", "ovr": "1.2", "bat": "301236", "r_t": "0", "bowl": "300619", "r": "0", "comm": "on a length, shaping back in, defended to mid-on with a straight bat", "x": "152", "y": "243", "o_a": "1.2", "z": "5"}, {"o_u": "1.05", "ovr": "1.3", "bat": "301236", "r_t": "0", "bowl": "300619", "r": "0", "comm": "short of a length, middle and leg, punched to mid-on", "x": "135", "y": "187", "o_a": "1.3", "z": "6"}, {"o_u": "1.06", "ovr": "1.4", "bat": "301236", "r_t": "0", "bowl": "300619", "r": "0", "comm": "on a length, quite sharp at 139ks, defended off the back foot", "x": "230", "y": "189", "o_a": "1.4", "z": "3"}, {"o_u": "1.07", "ovr": "1.5", "bat": "301236", "r_t": "4", "bowl": "300619", "r": "4", "comm": "wide length ball, drives through it with an open face. Beats point and cover. Lovely square drive. Rubs salt into that wound from the drop in the first over", "x": "353", "y": "175", "o_a": "1.5", "z": "3"}, {"o_u": "1.08", "ovr": "1.6", "bat": "301236", "r_t": "1", "bowl": "300619", "r": "1", "comm": "short of a length, pitches middle and leg, angles outside off, hits the inside edge", "x": "149", "y": "125", "o_a": "1.6", "z": "8"}, {"o_u": "2.01", "ovr": "2.1", "bat": "301236", "r_t": "1", "bowl": "56007", "r": "1", "comm": "length ball, on the pads, dropped into the leg side for one", "x": "125", "y": "199", "o_a": "2.1", "z": "6"}, {"o_u": "2.02", "ovr": "2.2", "bat": "48472", "r_t": "0", "bowl": "56007", "r": "0", "comm": "short of a length, angling in, defended to midwicket", "x": "236", "y": "194", "o_a": "2.2", "z": "3"}, {"o_u": "2.03", "ovr": "2.3", "bat": "48472", "r_t": "1", "bowl": "56007", "r": "1", "comm": "clipped away off the hip for a single", "x": "327", "y": "104", "o_a": "2.3", "z": "2"}, {"o_u": "2.04", "ovr": "2.4", "bat": "301236", "r_t": "0", "bowl": "56007", "r": "0", "comm": "length ball outside off, left alone", "x": "0", "y": "0", "o_a": "2.4", "z": "0"}, {"o_u": "2.05", "ovr": "2.5", "bat": "301236", "r_t": "0", "bowl": "56007", "r": "0", "comm": "length ball, just outside off, angling away, left alone", "x": "0", "y": "0", "o_a": "2.5", "z": "0"}, {"o_u": "2.06", "ovr": "2.6", "bat": "301236", "r_t": "1", "bowl": "56007", "r": "1", "comm": "<b>Thirimanne continues to live dangerously</b>. This is short of a length, outside off, and he chases it. Edges it just fine of that short gully", "x": "317", "y": "93", "o_a": "2.6", "z": "2"}, {"o_u": "3.01", "ovr": "3.1", "bat": "301236", "r_t": "1", "bowl": "300619", "r": "1", "comm": "short of a length, outside off, steered away to third man for one", "x": "303", "y": "85", "o_a": "3.1", "z": "2"}, {"o_u": "3.02", "ovr": "3.2", "bat": "48472", "r_t": "1", "bowl": "300619", "r": "1", "comm": "Dilshan drives on the up, with an open face, past the diving man at point", "x": "71", "y": "75", "o_a": "3.2", "z": "7"}, {"o_u": "3.03", "ovr": "3.3", "bat": "301236", "r_t": "0", "bowl": "300619", "r": "0", "comm": "bouncer, he ducks under it, Mushfiq has to leap in the air to just get a hand on it. Dilshan wants the bye, but Thirimanne is not alert", "x": "0", "y": "0", "o_a": "3.3", "z": "0"}, {"o_u": "3.04", "ovr": "3.4", "bat": "301236", "r_t": "0", "bowl": "300619", "r": "0", "comm": "short of a length, on the pads, defended back to him", "x": "160", "y": "197", "o_a": "3.4", "z": "5"}, {"o_u": "3.05", "ovr": "3.5", "bat": "301236", "r_t": "0", "bowl": "300619", "r": "0", "comm": "short of a length, gets it to rise towards the ribs, defended back to him", "x": "237", "y": "187", "o_a": "3.5", "z": "3"}, {"o_u": "3.06", "ovr": "3.6", "bat": "301236", "r_t": "1", "bowl": "300619", "r": "0", "comm": "wide, big wide down the leg side", "x": "0", "y": "0", "o_a": "3.6", "z": "0"}, {"o_u": "3.07", "ovr": "3.6", "bat": "301236", "r_t": "2", "bowl": "300619", "r": "2", "comm": "Thirmanne's charmed life continues. Flicks this in the air with a square leg in place, but gets it just wide of that man", "x": "65", "y": "182", "o_a": "3.6", "z": "6"}, {"o_u": "4.01", "ovr": "4.1", "bat": "48472", "r_t": "0", "bowl": "56007", "r": "0", "comm": "short of a length, on off, punched to mid-off", "x": "118", "y": "184", "o_a": "4.1", "z": "6"}, {"o_u": "4.02", "ovr": "4.2", "bat": "48472", "r_t": "1", "bowl": "56007", "r": "1", "comm": "short of a length again, from wide on the crease, pushed towards mid-on and steals a single", "x": "221", "y": "230", "o_a": "4.2", "z": "4"}, {"o_u": "4.03", "ovr": "4.3", "bat": "301236", "r_t": "0", "bowl": "56007", "r": "0", "comm": "length ball around off, trying to sucker him into another drive, but this time Thirmanne lets it go", "x": "0", "y": "0", "o_a": "4.3", "z": "0"}, {"o_u": "4.04", "ovr": "4.4", "bat": "301236", "r_t": "0", "bowl": "56007", "r": "0", "comm": "short of a length this time, he stays back and defends outside off", "x": "223", "y": "186", "o_a": "4.4", "z": "3"}, {"o_u": "4.05", "ovr": "4.5", "bat": "301236", "r_t": "0", "bowl": "56007", "r": "0", "comm": "nice drive as he gets close to the line of this length ball, but can't beat mid-off", "x": "221", "y": "249", "o_a": "4.5", "z": "4"}, {"o_u": "4.06", "ovr": "4.6", "bat": "301236", "r_t": "0", "bowl": "56007", "r": "0", "comm": "another sucker delivery outside off left alone by Thirimanne", "x": "0", "y": "0", "o_a": "4.6", "z": "0"}, {"o_u": "5.01", "ovr": "5.1", "bat": "48472", "r_t": "1", "bowl": "300619", "r": "1", "comm": "short of a length, just outside off, pushed wide of mid-off for one", "x": "137", "y": "231", "o_a": "5.1", "z": "5"}, {"o_u": "5.02", "ovr": "5.2", "bat": "301236", "r_t": "1", "bowl": "300619", "r": "0", "comm": "yet another wide down the leg side", "x": "0", "y": "0", "o_a": "5.2", "z": "0"}, {"o_u": "5.03", "ovr": "5.2", "bat": "301236", "r_t": "0", "bowl": "300619", "r": "0", "comm": "on a length, angling in, defended in front of off", "x": "159", "y": "196", "o_a": "5.2", "z": "5"}, {"o_u": "5.04", "ovr": "5.3", "bat": "301236", "r_t": "1", "bowl": "300619", "r": "0", "comm": "and yet another wide, angling well down the leg side", "x": "0", "y": "0", "o_a": "5.3", "z": "0"}, {"o_u": "5.05", "ovr": "5.3", "bat": "301236", "r_t": "2", "bowl": "300619", "r": "2", "comm": "angling too far into the pads, and has been picked away for an easy couple straight of fine leg", "x": "153", "y": "15", "o_a": "5.3", "z": "8"}, {"o_u": "5.06", "ovr": "5.4", "bat": "301236", "r_t": "0", "bowl": "300619", "r": "0", "comm": "accurate now, on a length, angling in towards off, defended from the crease", "x": "237", "y": "186", "o_a": "5.4", "z": "3"}, {"o_u": "5.07", "ovr": "5.5", "bat": "301236", "r_t": "0", "bowl": "300619", "r": "0", "comm": "short of a length, looks to go hard into the off side, mistimes it", "x": "243", "y": "172", "o_a": "5.5", "z": "3"}, {"o_u": "5.08", "ovr": "5.6", "bat": "301236", "r_t": "3", "bowl": "300619", "r": "3", "comm": "half-volley this time, just outside off, driven with an open face, past the diving man at cover", "x": "324", "y": "242", "o_a": "5.6", "z": "3"}, {"o_u": "6.01", "ovr": "6.1", "bat": "301236", "r_t": "0", "bowl": "56007", "r": "0", "comm": "on a length, middle and leg, bunted towards mid-on. Thiri wants a single, but Dilshan sends him back", "x": "162", "y": "199", "o_a": "6.1", "z": "5"}, {"o_u": "6.02", "ovr": "6.2", "bat": "301236", "r_t": "0", "bowl": "56007", "r": "0", "comm": "on a length, pitches off, angles away, left alone", "x": "0", "y": "0", "o_a": "6.2", "z": "0"}, {"o_u": "6.03", "ovr": "6.3", "bat": "301236", "r_t": "0", "bowl": "56007", "r": "0", "comm": "moves around in the crease, first towards off, then backing away and stepping down. All of that amounts to nothing as he is beaten on the drive to a short-of-a-length delivery. <b>Draws an optimistic appeal from Mushfiq</b>", "x": "0", "y": "0", "o_a": "6.3", "z": "0"}, {"o_u": "6.04", "ovr": "6.4", "bat": "301236", "r_t": "3", "bowl": "56007", "r": "3", "comm": "rare leg-side half-volley, and Thirimanne clips it off the toes, past midwicket", "x": "45", "y": "261", "o_a": "6.4", "z": "6"}, {"o_u": "6.05", "ovr": "6.5", "bat": "48472", "r_t": "0", "bowl": "56007", "r": "0", "comm": "short of a length, angling in from wide on the crease, punched to midwicket", "x": "247", "y": "190", "o_a": "6.5", "z": "3"}, {"o_u": "6.06", "ovr": "6.6", "bat": "48472", "r_t": "0", "bowl": "56007", "r": "0", "comm": "stays short of a length again, defended to mid-on", "x": "207", "y": "206", "o_a": "6.6", "z": "4"}, {"o_u": "7.01", "ovr": "7.1", "bat": "301236", "r_t": "1", "bowl": "538506", "r": "1", "comm": "starts outside leg, tucked away for an easy single", "x": "117", "y": "48", "o_a": "7.1", "z": "8"}, {"o_u": "7.02", "ovr": "7.2", "bat": "48472", "r_t": "1", "bowl": "538506", "r": "0", "comm": "wide length ball, Dilshan goes after it, is beaten, but this is called a wide. Not possible to reach balls this wide", "x": "0", "y": "0", "o_a": "7.2", "z": "0"}, {"o_u": "7.03", "ovr": "7.2", "bat": "48472", "r_t": "4", "bowl": "538506", "r": "4", "comm": "wide half-volley, Dilshan plants his front foot down, and crashes this wide of mid-off for four", "x": "43", "y": "297", "o_a": "7.2", "z": "6"}, {"o_u": "7.04", "ovr": "7.3", "bat": "48472", "r_t": "0", "bowl": "538506", "r": "0", "comm": "looks to drive at another half-volley, but the bat face closes a little and ends up hitting this back to the bowler. Think this one doesn't quite come on to the bat", "x": "166", "y": "202", "o_a": "7.3", "z": "5"}, {"o_u": "7.05", "ovr": "7.4", "bat": "48472", "r_t": "4", "bowl": "538506", "r": "4", "comm": "tries the bouncer, gets it shoulder high, and Dilshan gets stuck into it, pulling it over square leg", "x": "354", "y": "200", "o_a": "7.4", "z": "3"}, {"o_u": "7.06", "ovr": "7.5", "bat": "48472", "r_t": "0", "bowl": "538506", "r": "0", "comm": "short and wide, and Taskin is lucky Dilshan has found cover-point with the cut shot", "x": "112", "y": "188", "o_a": "7.5", "z": "6"}, {"o_u": "7.07", "ovr": "7.6", "bat": "48472", "r_t": "2", "bowl": "538506", "r": "2", "comm": "on a length, pushed towards mid-off, he sets off for a quick single, and gets an overthrow from the ricochet off the stumps at the non-striker's end", "x": "153", "y": "229", "o_a": "7.6", "z": "5"}, {"o_u": "8.01", "ovr": "8.1", "bat": "301236", "r_t": "0", "bowl": "56007", "r": "0", "comm": "short of a length, on the pads, defended to leg", "x": "149", "y": "192", "o_a": "8.1", "z": "6"}, {"o_u": "8.02", "ovr": "8.2", "bat": "301236", "r_t": "0", "bowl": "56007", "r": "0", "comm": "full, on off, slight shape away, runs off the outside half of the bat to cover", "x": "234", "y": "201", "o_a": "8.2", "z": "3"}, {"o_u": "8.03", "ovr": "8.3", "bat": "301236", "r_t": "0", "bowl": "56007", "r": "0", "comm": "on a length, on off, no room, defended watchfully", "x": "247", "y": "190", "o_a": "8.3", "z": "3"}, {"o_u": "8.04", "ovr": "8.4", "bat": "301236", "r_t": "2", "bowl": "56007", "r": "2", "comm": "mid-off is wide, which is why he has thrown his arms at a full ball and hit it through mid-off in the air. Gets a couple. Soumya Sarkar has given it a quick chase, and restricted them to two", "x": "248", "y": "322", "o_a": "8.4", "z": "4"}, {"o_u": "8.05", "ovr": "8.5", "bat": "301236", "r_t": "4", "bowl": "56007", "r": "4", "comm": "<b>Thirimanne is a cat today</b>. Has a life after life. Might end up with nine. He edges Mashrafe outside off again, playing a nothing drive to a length ball. The first slip is wide, this is flying wide of the keeper, Mushfiqur wants to go for it and bails out at the last moment. Aww. Mushfiq should have gone for it. The slip is wide. Thirimanne gets four for it", "x": "215", "y": "9", "o_a": "8.5", "z": "1"}, {"o_u": "8.06", "ovr": "8.6", "bat": "301236", "r_t": "0", "bowl": "56007", "r": "0", "comm": "short of a length, outside off, left alone", "x": "0", "y": "0", "o_a": "8.6", "z": "0"}, {"o_u": "9.01", "ovr": "9.1", "bat": "48472", "r_t": "0", "bowl": "56143", "r": "0", "comm": "down the wicket, too close to the pitch of the ball, plays it back to Shakib", "x": "174", "y": "200", "o_a": "9.1", "z": "5"}, {"o_u": "9.02", "ovr": "9.2", "bat": "48472", "r_t": "1", "bowl": "56143", "r": "1", "comm": "driven down to long-off for one", "x": "152", "y": "326", "o_a": "9.2", "z": "5"}, {"o_u": "9.03", "ovr": "9.3", "bat": "301236", "r_t": "3", "bowl": "56143", "r": "3", "comm": "<b>Oh Thirimanne</b>. He should walk out of the ground, and walk along the Yarra and walk right into the Crown Casino. Another edge as he pushes at one outside off, but this too flies wide of slip", "x": "244", "y": "41", "o_a": "9.3", "z": "1"}, {"o_u": "9.04", "ovr": "9.4", "bat": "48472", "r_t": "0", "bowl": "56143", "r": "0", "comm": "tossed up, middle and leg, defended", "x": "214", "y": "197", "o_a": "9.4", "z": "3"}, {"o_u": "9.05", "ovr": "9.5", "bat": "48472", "r_t": "1", "bowl": "56143", "r": "1", "comm": "presses forward before going back to punch this down the ground. Short straight cover puts a dive in, but can't save the single", "x": "141", "y": "225", "o_a": "9.5", "z": "5"}, {"o_u": "9.06", "ovr": "9.6", "bat": "301236", "r_t": "0", "bowl": "56143", "r": "0", "comm": "stays back to punch this to short straight midwicket", "x": "137", "y": "214", "o_a": "9.6", "z": "5"}, {"o_u": "10.01", "ovr": "10.1", "bat": "48472", "r_t": "0", "bowl": "56007", "r": "0", "comm": "full and wide, driven wide of mid-off, but Thirimanne is ball-watching on what should be an easy single. Dilshan makes it back in time", "x": "130", "y": "241", "o_a": "10.1", "z": "5"}, {"o_u": "10.02", "ovr": "10.2", "bat": "48472", "r_t": "0", "bowl": "56007", "r": "0", "comm": "looks to play this slightly short delivery square on the wicket, and is beaten. Not short enough. An optimistic half shout for an edge, but there isn't any", "x": "0", "y": "0", "o_a": "10.2", "z": "0"}, {"o_u": "10.03", "ovr": "10.3", "bat": "48472", "r_t": "2", "bowl": "56007", "r": "2", "comm": "drives this with an open face, wide of deep cover, comes back for a second", "x": "42", "y": "227", "o_a": "10.3", "z": "6"}, {"o_u": "10.04", "ovr": "10.4", "bat": "48472", "r_t": "0", "bowl": "56007", "r": "0", "comm": "another powerful drive but straight to mid-off", "x": "155", "y": "236", "o_a": "10.4", "z": "5"}, {"o_u": "10.05", "ovr": "10.5", "bat": "48472", "r_t": "0", "bowl": "56007", "r": "0", "comm": "full, just outside off, driven again, but straight to mid-off. Again the bat face closes a touch", "x": "153", "y": "248", "o_a": "10.5", "z": "5"}, {"o_u": "10.06", "ovr": "10.6", "bat": "48472", "r_t": "4", "bowl": "56007", "r": "4", "comm": "that's a half-tracker. Gentle long hop. Dilshan gets stuck into it again, and pulls it through midwicket for four", "x": "354", "y": "210", "o_a": "10.6", "z": "3"}, {"o_u": "11.01", "ovr": "11.1", "bat": "301236", "r_t": "0", "bowl": "56143", "r": "0", "comm": "tossed up outside off, pushed to mid-on", "x": "163", "y": "208", "o_a": "11.1", "z": "5"}, {"o_u": "11.02", "ovr": "11.2", "bat": "301236", "r_t": "0", "bowl": "56143", "r": "0", "comm": "stays back to defend a length ball with an open face", "x": "245", "y": "179", "o_a": "11.2", "z": "3"}, {"o_u": "11.03", "ovr": "11.3", "bat": "301236", "r_t": "0", "bowl": "56143", "r": "0", "comm": "short of a length, punched back to the bowler", "x": "171", "y": "199", "o_a": "11.3", "z": "5"}, {"o_u": "11.04", "ovr": "11.4", "bat": "301236", "r_t": "1", "bowl": "56143", "r": "1", "comm": "half-volley driven to long-on for one. They have taken the single although it has gone off Dilshan's pad at non-striker's end", "x": "132", "y": "314", "o_a": "11.4", "z": "5"}, {"o_u": "11.05", "ovr": "11.5", "bat": "48472", "r_t": "0", "bowl": "56143", "r": "0", "comm": "down the wicket to pad this away", "x": "141", "y": "178", "o_a": "11.5", "z": "6"}, {"o_u": "11.06", "ovr": "11.6", "bat": "48472", "r_t": "0", "bowl": "56143", "r": "0", "comm": "short of a length, defended to cover", "x": "114", "y": "201", "o_a": "11.6", "z": "6"}, {"o_u": "12.01", "ovr": "12.1", "bat": "301236", "r_t": "1", "bowl": "56025", "r": "1", "comm": "half-volley, driven to deep cover for one", "x": "323", "y": "216", "o_a": "12.1", "z": "3"}, {"o_u": "12.02", "ovr": "12.2", "bat": "48472", "r_t": "0", "bowl": "56025", "r": "0", "comm": "flighted outside off, pushed back to the bowler", "x": "159", "y": "202", "o_a": "12.2", "z": "5"}, {"o_u": "12.03", "ovr": "12.3", "bat": "48472", "r_t": "1", "bowl": "56025", "r": "1", "comm": "short of a length, worked into the leg side for one", "x": "251", "y": "194", "o_a": "12.3", "z": "3"}, {"o_u": "12.04", "ovr": "12.4", "bat": "301236", "r_t": "0", "bowl": "56025", "r": "0", "comm": "flighted on off, pushed to cover off the front foot", "x": "223", "y": "214", "o_a": "12.4", "z": "4"}, {"o_u": "12.05", "ovr": "12.5", "bat": "301236", "r_t": "0", "bowl": "56025", "r": "0", "comm": "fuller and flat, pushed with an open face", "x": "245", "y": "174", "o_a": "12.5", "z": "3"}, {"o_u": "12.06", "ovr": "12.6", "bat": "301236", "r_t": "0", "bowl": "56025", "r": "0", "comm": "flatter, Thirimanne stays back to defend", "x": "239", "y": "180", "o_a": "12.6", "z": "3"}, {"o_u": "13.01", "ovr": "13.1", "bat": "48472", "r_t": "0", "bowl": "56143", "r": "0", "comm": "pitched up on middle and leg, defended off the front foot", "x": "209", "y": "185", "o_a": "13.1", "z": "3"}, {"o_u": "13.02", "ovr": "13.2", "bat": "48472", "r_t": "0", "bowl": "56143", "r": "0", "comm": "down the track but too close to the ball, defends it back to him", "x": "170", "y": "200", "o_a": "13.2", "z": "5"}, {"o_u": "13.03", "ovr": "13.3", "bat": "48472", "r_t": "2", "bowl": "56143", "r": "2", "comm": "flatter, stays back although the ball is full, and punches it to deep cover for two", "x": "46", "y": "230", "o_a": "13.3", "z": "6"}, {"o_u": "13.04", "ovr": "13.4", "bat": "48472", "r_t": "0", "bowl": "56143", "r": "0", "comm": "down the wicket, not close to the pitch of the ball and pads this away", "x": "208", "y": "185", "o_a": "13.4", "z": "3"}, {"o_u": "13.05", "ovr": "13.5", "bat": "48472", "r_t": "0", "bowl": "56143", "r": "0", "comm": "down the wicket, again not to the pitch of the ball, and defends this towards mid-on", "x": "219", "y": "220", "o_a": "13.5", "z": "4"}, {"o_u": "13.06", "ovr": "13.6", "bat": "48472", "r_t": "0", "bowl": "56143", "r": "0", "comm": "nearly yorks him with a full flat one. Dilshan keeps it out", "x": "166", "y": "190", "o_a": "13.6", "z": "5"}, {"o_u": "14.01", "ovr": "14.1", "bat": "301236", "r_t": "1", "bowl": "56025", "r": "1", "comm": "flighted, into the pads, driven to long-on for one", "x": "151", "y": "326", "o_a": "14.1", "z": "5"}, {"o_u": "14.02", "ovr": "14.2", "bat": "48472", "r_t": "1", "bowl": "56025", "r": "1", "comm": "short of a length, into the pads, worked away for one", "x": "334", "y": "195", "o_a": "14.2", "z": "3"}, {"o_u": "14.03", "ovr": "14.3", "bat": "301236", "r_t": "1", "bowl": "56025", "r": "1", "comm": "flighted into the pads again, and driven to long-on again", "x": "145", "y": "325", "o_a": "14.3", "z": "5"}, {"o_u": "14.04", "ovr": "14.4", "bat": "48472", "r_t": "4", "bowl": "56025", "r": "4", "comm": "lovely shot. Down the wicket, right to the pitch of the ball, makes a little bit of room to make some room, and drives him between mid-off and cover. All along the ground", "x": "101", "y": "346", "o_a": "14.4", "z": "5"}, {"o_u": "14.05", "ovr": "14.5", "bat": "48472", "r_t": "1", "bowl": "56025", "r": "1", "comm": "flatter, into the pads, worked to leg for one", "x": "321", "y": "163", "o_a": "14.5", "z": "2"}, {"o_u": "14.06", "ovr": "14.6", "bat": "301236", "r_t": "1", "bowl": "56025", "r": "1", "comm": "slower through the air, Thirimanne drops it towards cover and sneaks in a quick single", "x": "236", "y": "185", "o_a": "14.6", "z": "3"}, {"o_u": "15.01", "ovr": "15.1", "bat": "301236", "r_t": "1", "bowl": "56143", "r": "1", "comm": "flat delivery, he stays back and punches this to deep point for one", "x": "323", "y": "180", "o_a": "15.1", "z": "3"}, {"o_u": "15.02", "ovr": "15.2", "bat": "48472", "r_t": "0", "bowl": "56143", "r": "0", "comm": "tangled into the pads, swept away fine but can't beat short fine leg", "x": "229", "y": "115", "o_a": "15.2", "z": "1"}, {"o_u": "15.03", "ovr": "15.3", "bat": "48472", "r_t": "0", "bowl": "56143", "r": "0", "comm": "slower through the air, dropping in on a length on off, defended with an open face", "x": "123", "y": "182", "o_a": "15.3", "z": "6"}, {"o_u": "15.04", "ovr": "15.4", "bat": "48472", "r_t": "1", "bowl": "56143", "r": "1", "comm": "flatter and quicker, punched to deep cover for one", "x": "33", "y": "200", "o_a": "15.4", "z": "6"}, {"o_u": "15.05", "ovr": "15.5", "bat": "301236", "r_t": "2", "bowl": "56143", "r": "2", "comm": "down the wicket to chip this over cover for two", "x": "303", "y": "243", "o_a": "15.5", "z": "3"}, {"o_u": "15.06", "ovr": "15.6", "bat": "301236", "r_t": "1", "bowl": "56143", "r": "1", "comm": "flat, on the pads, worked away for an easy single", "x": "72", "y": "159", "o_a": "15.6", "z": "7"}, {"o_u": "16.01", "ovr": "16.1", "bat": "301236", "r_t": "1", "bowl": "538506", "r": "1", "comm": "on length outside off angling across, driven late behind square on off for one", "x": "335", "y": "179", "o_a": "16.1", "z": "3"}, {"o_u": "16.02", "ovr": "16.2", "bat": "48472", "r_t": "2", "bowl": "538506", "r": "2", "comm": "touch back of length towards middle and leg, tucked to deep midwicket for two", "x": "308", "y": "210", "o_a": "16.2", "z": "3"}, {"o_u": "16.03", "ovr": "16.3", "bat": "48472", "r_t": "0", "bowl": "538506", "r": "0", "comm": "good length ball this time towards off, he wants to steer it to leg but gets an inside edge on the pads", "x": "217", "y": "187", "o_a": "16.3", "z": "3"}, {"o_u": "16.04", "ovr": "16.4", "bat": "48472", "r_t": "0", "bowl": "538506", "r": "0", "comm": "full on off, driven firmly down the ground to mid off", "x": "146", "y": "253", "o_a": "16.4", "z": "5"}, {"o_u": "16.05", "ovr": "16.5", "bat": "48472", "r_t": "1", "bowl": "538506", "r": "1", "comm": "good length on off, pushed a bit wide of cover point for one", "x": "113", "y": "194", "o_a": "16.5", "z": "6"}, {"o_u": "16.06", "ovr": "16.6", "bat": "301236", "r_t": "0", "bowl": "538506", "r": "0", "comm": "just back of length on off and angling across, pushed into the covers. Tidy over from Taskin", "x": "226", "y": "181", "o_a": "16.6", "z": "3"}, {"o_u": "17.01", "ovr": "17.1", "bat": "48472", "r_t": "1", "bowl": "56143", "r": "1", "comm": "bit of flight just outside off, pushed wide of cover for one", "x": "124", "y": "201", "o_a": "17.1", "z": "6"}, {"o_u": "17.02", "ovr": "17.2", "bat": "301236", "r_t": "0", "bowl": "56143", "r": "0", "comm": "charges down and muscles a drive straight to mid off", "x": "211", "y": "253", "o_a": "17.2", "z": "4"}, {"o_u": "17.03", "ovr": "17.3", "bat": "301236", "r_t": "1", "bowl": "56143", "r": "1", "comm": "turning in from off and middle, helped to the leg side easily for one", "x": "71", "y": "140", "o_a": "17.3", "z": "7"}, {"o_u": "17.04", "ovr": "17.4", "bat": "48472", "r_t": "0", "bowl": "56143", "r": "0", "comm": "flat and short just outside off, punched to cover off the back foot", "x": "134", "y": "217", "o_a": "17.4", "z": "5"}, {"o_u": "17.05", "ovr": "17.5", "bat": "48472", "r_t": "1", "bowl": "56143", "r": "1", "comm": "flat on the leg side now, pulled late to deep backward square for one", "x": "326", "y": "123", "o_a": "17.5", "z": "2"}, {"o_u": "17.06", "ovr": "17.6", "bat": "301236", "r_t": "0", "bowl": "56143", "r": "0", "comm": "full on the pads, tucked late but straight to short fine leg. Just three from the over", "x": "159", "y": "109", "o_a": "17.6", "z": "8"}, {"o_u": "18.01", "ovr": "18.1", "bat": "48472", "r_t": "0", "bowl": "538506", "r": "0", "comm": "quick, back of length delivery outside off, Dilshan chases but it seams away to beat him", "x": "0", "y": "0", "o_a": "18.1", "z": "0"}, {"o_u": "18.02", "ovr": "18.2", "bat": "48472", "r_t": "0", "bowl": "538506", "r": "0", "comm": "length delivery angled towards the pads now, driven down to mid on", "x": "206", "y": "245", "o_a": "18.2", "z": "4"}, {"o_u": "18.03", "ovr": "18.3", "bat": "48472", "r_t": "0", "bowl": "538506", "r": "0", "comm": "full on the stumps, driven back firmly and Taskin stops it", "x": "162", "y": "197", "o_a": "18.3", "z": "5"}, {"o_u": "18.04", "ovr": "18.4", "bat": "48472", "r_t": "0", "bowl": "538506", "r": "0", "comm": "just back of length outside off with some room, Dilshan cuts it late to backward point", "x": "111", "y": "138", "o_a": "18.4", "z": "7"}, {"o_u": "18.05", "ovr": "18.5", "bat": "48472", "r_t": "0", "bowl": "538506", "r": "0", "comm": "on length outside off, pushed towards point and Dilshan is sent back for the single", "x": "115", "y": "166", "o_a": "18.5", "z": "6"}, {"o_u": "18.06", "ovr": "18.6", "bat": "48472", "r_t": "0", "bowl": "538506", "r": "0", "comm": "fullish outside off, Dilshan drives and gets a thickish edge to the leg side. That's a <b>maiden</b>", "x": "228", "y": "183", "o_a": "18.6", "z": "3"}, {"o_u": "19.01", "ovr": "19.1", "bat": "301236", "r_t": "1", "bowl": "56025", "r": "1", "comm": "slow, length delivery outside off, punched off the back foot to sweeper cover", "x": "336", "y": "221", "o_a": "19.1", "z": "3"}, {"o_u": "19.02", "ovr": "19.2", "bat": "48472", "r_t": "1", "bowl": "56025", "r": "0", "comm": "this one was flatter, Dilshan takes out his reverse sweeps and it goes under his bat down leg. Premeditated shot that one", "x": "0", "y": "0", "o_a": "19.2", "z": "0"}, {"o_u": "19.03", "ovr": "19.3", "bat": "301236", "r_t": "0", "bowl": "56025", "r": "0", "comm": "on length on middle, makes room and pushes to midwicket", "x": "144", "y": "225", "o_a": "19.3", "z": "5"}, {"o_u": "19.04", "ovr": "19.4", "bat": "301236", "r_t": "0", "bowl": "56025", "r": "0", "comm": "makes a bit of room again and cuts the ball on the off stump to short third man", "x": "237", "y": "137", "o_a": "19.4", "z": "2"}, {"o_u": "19.05", "ovr": "19.5", "bat": "301236", "r_t": "1", "bowl": "56025", "r": "1", "comm": "pushes this one down to long on off the back foot for one", "x": "149", "y": "312", "o_a": "19.5", "z": "5"}, {"o_u": "19.06", "ovr": "19.6", "bat": "48472", "r_t": "4", "bowl": "56025", "r": "4", "comm": "shorter and flat towards off and Dilshan rocks back to swat-pull it between long on and deep midwicket, finds the gap for four", "x": "329", "y": "282", "o_a": "19.6", "z": "3"}, {"o_u": "20.01", "ovr": "20.1", "bat": "301236", "r_t": "0", "bowl": "538506", "r": "0", "comm": "angles across the length delivery outside off, driven late to point", "x": "247", "y": "160", "o_a": "20.1", "z": "2"}, {"o_u": "20.02", "ovr": "20.2", "bat": "301236", "r_t": "1", "bowl": "538506", "r": "1", "comm": "closer to the off stump, Thirimanne slices it to third man for one", "x": "287", "y": "72", "o_a": "20.2", "z": "2"}, {"o_u": "20.03", "ovr": "20.3", "bat": "48472", "r_t": "4", "bowl": "538506", "r": "4", "comm": "bit too full on the stumps and Dilshan crunches it straight down the ground for another four! Full face of the bat, sweet timing, nobody could chase that", "x": "194", "y": "358", "o_a": "20.3", "z": "4"}, {"o_u": "20.04", "ovr": "20.4", "bat": "48472", "r_t": "0", "bowl": "538506", "r": "0", "comm": "pitches this one shorter outside off and Dilshan cuts it straight to point", "x": "113", "y": "161", "o_a": "20.4", "z": "7"}, {"o_u": "20.05", "ovr": "20.5", "bat": "48472", "r_t": "4", "bowl": "538506", "r": "4", "comm": "full again, this time outside off and Dilshan drives it nicely through the covers this time, four more!", "x": "66", "y": "318", "o_a": "20.5", "z": "5"}, {"o_u": "20.06", "ovr": "20.6", "bat": "48472", "r_t": "4", "bowl": "538506", "r": "4", "comm": "he's taking them on, four more for his <b>fifty</b>! He expected the short ball, stayed back and pulled it over midwicket", "x": "332", "y": "271", "o_a": "20.6", "z": "3"}, {"o_u": "21.01", "ovr": "21.1", "bat": "301236", "r_t": "0", "bowl": "373538", "r": "0", "comm": "turning in from middle, pushed to midwicket", "x": "143", "y": "209", "o_a": "21.1", "z": "5"}, {"o_u": "21.02", "ovr": "21.2", "bat": "301236", "r_t": "1", "bowl": "373538", "r": "1", "comm": "full on leg, driven down by making some room to long on", "x": "156", "y": "332", "o_a": "21.2", "z": "5"}, {"o_u": "21.03", "ovr": "21.3", "bat": "48472", "r_t": "0", "bowl": "373538", "r": "0", "comm": "goes on the back foot and punches to cover", "x": "121", "y": "201", "o_a": "21.3", "z": "6"}, {"o_u": "21.04", "ovr": "21.4", "bat": "48472", "r_t": "1", "bowl": "373538", "r": "1", "comm": "touch back of length on middle and leg, pushed down to long on", "x": "217", "y": "333", "o_a": "21.4", "z": "4"}, {"o_u": "21.05", "ovr": "21.5", "bat": "301236", "r_t": "0", "bowl": "373538", "r": "0", "comm": "<b>misses a stumping</b>! This one went past Thirimanne as he came down the track, was beaten outside off and Mushfiqur spills the ball", "x": "0", "y": "0", "o_a": "21.5", "z": "0"}, {"o_u": "21.06", "ovr": "21.6", "bat": "301236", "r_t": "4", "bowl": "373538", "r": "4", "comm": "replies by hitting it over the bowler. Got a full delivery and smashed it straight down the ground in the air to beat long on and long off", "x": "166", "y": "356", "o_a": "21.6", "z": "5"}, {"o_u": "22.01", "ovr": "22.1", "bat": "48472", "r_t": "2", "bowl": "300619", "r": "2", "comm": "full outside off, driven through the covers wide of sweeper cover. Dilshan wants two and a widish throw makes sure he's safe", "x": "29", "y": "130", "o_a": "22.1", "z": "7"}, {"o_u": "22.02", "ovr": "22.2", "bat": "48472", "r_t": "0", "bowl": "300619", "r": "0", "comm": "too full again, on off, Dilshan powers a drive back and Rubel stops it with his right foot. Looks like he has hurt himself", "x": "164", "y": "204", "o_a": "22.2", "z": "5"}, {"o_u": "22.03", "ovr": "22.3", "bat": "48472", "r_t": "1", "bowl": "300619", "r": "1", "comm": "back of length outside off, he pulls it over midwicket for one. No time for the second", "x": "316", "y": "201", "o_a": "22.3", "z": "3"}, {"o_u": "22.04", "ovr": "22.4", "bat": "301236", "r_t": "0", "bowl": "300619", "r": "0", "comm": "room on offer well outside off, it was shortish too, Thirimanne slashes and misses", "x": "0", "y": "0", "o_a": "22.4", "z": "0"}, {"o_u": "22.05", "ovr": "22.5", "bat": "301236", "r_t": "1", "bowl": "300619", "r": "1", "comm": "good ball - yorker on the leg stump, Thirimanne digs it out on off for one", "x": "320", "y": "228", "o_a": "22.5", "z": "3"}, {"o_u": "22.06", "ovr": "22.6", "bat": "48472", "r_t": "1", "bowl": "300619", "r": "1", "comm": "outside off now, guides it to third man for one", "x": "99", "y": "49", "o_a": "22.6", "z": "8"}, {"o_u": "23.01", "ovr": "23.1", "bat": "48472", "r_t": "1", "bowl": "373538", "r": "1", "comm": "touch short around off, pulled off the back foot to deep midwicket for one", "x": "326", "y": "229", "o_a": "23.1", "z": "3"}, {"o_u": "23.02", "ovr": "23.2", "bat": "301236", "r_t": "1", "bowl": "373538", "r": "1", "comm": "on leg stump, he goes back and pushes it down to long on for one for his <b>fifty</b>", "x": "125", "y": "302", "o_a": "23.2", "z": "5"}, {"o_u": "23.03", "ovr": "23.3", "bat": "48472", "r_t": "2", "bowl": "373538", "r": "2", "comm": "flatter and fuller well outside off, chops it to deep point for two quick runs", "x": "38", "y": "148", "o_a": "23.3", "z": "7"}, {"o_u": "23.04", "ovr": "23.4", "bat": "48472", "r_t": "1", "bowl": "373538", "r": "1", "comm": "flighted full toss on off, flicked to the leg side for one", "x": "267", "y": "313", "o_a": "23.4", "z": "4"}, {"o_u": "23.05", "ovr": "23.5", "bat": "301236", "r_t": "0", "bowl": "373538", "r": "0", "comm": "flat on middle, makes room and cuts it to cover point", "x": "243", "y": "201", "o_a": "23.5", "z": "3"}, {"o_u": "23.06", "ovr": "23.6", "bat": "301236", "r_t": "1", "bowl": "373538", "r": "1", "comm": "fullish on middle and leg, tucked on the leg side off the pads for one", "x": "97", "y": "177", "o_a": "23.6", "z": "6"}, {"o_u": "24.01", "ovr": "24.1", "bat": "301236", "r_t": "1", "bowl": "300619", "r": "1", "comm": "room outside off, cuts guides it easily to third man for one", "x": "301", "y": "79", "o_a": "24.1", "z": "2"}, {"o_u": "24.02", "ovr": "24.2", "bat": "48472", "r_t": "1", "bowl": "300619", "r": "1", "comm": "angled in, pulled with the angle to deep backward square for one", "x": "329", "y": "153", "o_a": "24.2", "z": "2"}, {"o_u": "24.03", "ovr": "24.3", "bat": "301236", "r_t": "0", "bowl": "300619", "r": "0", "comm": "straight to third man, the stand is broken! Rubel banged in a short ball just outside off, Thirimanne didn't move much and only ramped it with the face of the bat to third man. Taskin should have come forward a little bit but completed a low catch successfully in the end", "x": "278", "y": "56", "o_a": "24.3", "z": "1"}, {"o_u": "24.04", "ovr": "24.4", "bat": "50710", "r_t": "0", "bowl": "300619", "r": "0", "comm": "length delivery around off stump, pushed into the covers", "x": "227", "y": "185", "o_a": "24.4", "z": "3"}, {"o_u": "24.05", "ovr": "24.5", "bat": "50710", "r_t": "0", "bowl": "300619", "r": "0", "comm": "touch back of length on off, Sanga defends on the leg side", "x": "134", "y": "212", "o_a": "24.5", "z": "5"}, {"o_u": "24.06", "ovr": "24.6", "bat": "50710", "r_t": "0", "bowl": "300619", "r": "0", "comm": "bangs in the bouncer, Sanga ducks and it's not a wide", "x": "0", "y": "0", "o_a": "24.6", "z": "0"}, {"o_u": "25.01", "ovr": "25.1", "bat": "48472", "r_t": "0", "bowl": "56007", "r": "0", "comm": "short of length outside the off stump, pushed to cover off the back foot", "x": "117", "y": "199", "o_a": "25.1", "z": "6"}, {"o_u": "25.02", "ovr": "25.2", "bat": "48472", "r_t": "2", "bowl": "56007", "r": "2", "comm": "offcutter from outside off, Dilshan slices it late wide of third man for two", "x": "41", "y": "107", "o_a": "25.2", "z": "7"}, {"o_u": "25.03", "ovr": "25.3", "bat": "48472", "r_t": "1", "bowl": "56007", "r": "1", "comm": "short ball towards the batsman, tucked to the cover region for one", "x": "91", "y": "167", "o_a": "25.3", "z": "6"}, {"o_u": "25.04", "ovr": "25.4", "bat": "50710", "r_t": "1", "bowl": "56007", "r": "1", "comm": "length delivery outside off, pushes wide of point with soft hands to get off the mark", "x": "232", "y": "182", "o_a": "25.4", "z": "3"}, {"o_u": "25.05", "ovr": "25.5", "bat": "48472", "r_t": "0", "bowl": "56007", "r": "0", "comm": "angled in towards the batsman from back of length, can't clear midwicket", "x": "234", "y": "189", "o_a": "25.5", "z": "3"}, {"o_u": "25.06", "ovr": "25.6", "bat": "48472", "r_t": "1", "bowl": "56007", "r": "1", "comm": "full on the pads now, driven wide of midwicket for one now", "x": "277", "y": "192", "o_a": "25.6", "z": "3"}, {"o_u": "26.01", "ovr": "26.1", "bat": "48472", "r_t": "1", "bowl": "300619", "r": "1", "comm": "length delivery angled in, steered to deep midwicket for one", "x": "275", "y": "198", "o_a": "26.1", "z": "3"}, {"o_u": "26.02", "ovr": "26.2", "bat": "50710", "r_t": "0", "bowl": "300619", "r": "0", "comm": "doesn't offer any room - right on off stump on length, Sanga defends it back", "x": "182", "y": "192", "o_a": "26.2", "z": "4"}, {"o_u": "26.03", "ovr": "26.3", "bat": "50710", "r_t": "4", "bowl": "300619", "r": "4", "comm": "Sanga does a Thirimanne but plays it fine for four. Got a short ball from Rubel, he stayed back and ramped it fine over the slips for four", "x": "225", "y": "10", "o_a": "26.3", "z": "1"}, {"o_u": "26.04", "ovr": "26.4", "bat": "50710", "r_t": "1", "bowl": "300619", "r": "1", "comm": "just outside off, pushed with soft hands into the covers for a quick single", "x": "238", "y": "170", "o_a": "26.4", "z": "3"}, {"o_u": "26.05", "ovr": "26.5", "bat": "48472", "r_t": "0", "bowl": "300619", "r": "0", "comm": "muscles the widish delivery to point, Sanga comes nearly halfway down the pitch and goes back just in time", "x": "116", "y": "161", "o_a": "26.5", "z": "7"}, {"o_u": "26.06", "ovr": "26.6", "bat": "48472", "r_t": "0", "bowl": "300619", "r": "0", "comm": "on length on the stumps, he defends it back", "x": "182", "y": "193", "o_a": "26.6", "z": "4"}, {"o_u": "27.01", "ovr": "27.1", "bat": "50710", "r_t": "0", "bowl": "538506", "r": "0", "comm": "length delivery on middle and leg, tucked to midwicket", "x": "125", "y": "180", "o_a": "27.1", "z": "6"}, {"o_u": "27.02", "ovr": "27.2", "bat": "50710", "r_t": "0", "bowl": "538506", "r": "0", "comm": "touch shorter towards the off stump, Sanga defends it back", "x": "174", "y": "193", "o_a": "27.2", "z": "5"}, {"o_u": "27.03", "ovr": "27.3", "bat": "50710", "r_t": "2", "bowl": "538506", "r": "2", "comm": "outside the leg stump now, glanced down the leg side easily and they come back for two", "x": "132", "y": "30", "o_a": "27.3", "z": "8"}, {"o_u": "27.04", "ovr": "27.4", "bat": "50710", "r_t": "1", "bowl": "538506", "r": "1", "comm": "still on the leg stump, steered to deep backward square for one more", "x": "59", "y": "161", "o_a": "27.4", "z": "7"}, {"o_u": "27.05", "ovr": "27.5", "bat": "48472", "r_t": "0", "bowl": "538506", "r": "0", "comm": "back of length on the off stumps, defends solidly into the covers", "x": "125", "y": "188", "o_a": "27.5", "z": "6"}, {"o_u": "27.06", "ovr": "27.6", "bat": "48472", "r_t": "1", "bowl": "538506", "r": "1", "comm": "full and outside off, slices it late to third man for one", "x": "85", "y": "51", "o_a": "27.6", "z": "8"}, {"o_u": "28.01", "ovr": "28.1", "bat": "48472", "r_t": "0", "bowl": "300619", "r": "0", "comm": "full on the stumps, pushed back to the bowler. Rubel jumps and stops with both hands, gets a big cheer from the crowd", "x": "172", "y": "193", "o_a": "28.1", "z": "5"}, {"o_u": "28.02", "ovr": "28.2", "bat": "48472", "r_t": "0", "bowl": "300619", "r": "0", "comm": "huge cheer this time as Bijoy dives to his right to stop the powerful cover drive", "x": "125", "y": "200", "o_a": "28.2", "z": "6"}, {"o_u": "28.03", "ovr": "28.3", "bat": "48472", "r_t": "0", "bowl": "300619", "r": "0", "comm": "slower offcutter outside off, cut off the back foot towards point", "x": "134", "y": "125", "o_a": "28.3", "z": "7"}, {"o_u": "28.04", "ovr": "28.4", "bat": "48472", "r_t": "1", "bowl": "300619", "r": "1", "comm": "tucks the ball from off and middle towards midwicket, they set off for the quick one, good early call. There's an overthrow but no time to come back for the second", "x": "248", "y": "180", "o_a": "28.4", "z": "3"}, {"o_u": "28.05", "ovr": "28.5", "bat": "50710", "r_t": "1", "bowl": "300619", "r": "1", "comm": "back of length on leg stump, tucked off the hips to the leg side for one", "x": "93", "y": "158", "o_a": "28.5", "z": "7"}, {"o_u": "28.06", "ovr": "28.6", "bat": "48472", "r_t": "1", "bowl": "300619", "r": "1", "comm": "short of length ball angling in, pulled with the angle to deep fine leg", "x": "270", "y": "59", "o_a": "28.6", "z": "1"}, {"o_u": "29.01", "ovr": "29.1", "bat": "48472", "r_t": "1", "bowl": "56025", "r": "1", "comm": "turning in from just outside off, helped to the leg side for one", "x": "304", "y": "191", "o_a": "29.1", "z": "3"}, {"o_u": "29.02", "ovr": "29.2", "bat": "50710", "r_t": "1", "bowl": "56025", "r": "1", "comm": "outside off with a bit of turn, turned to long on off the back foot for one", "x": "70", "y": "273", "o_a": "29.2", "z": "6"}, {"o_u": "29.03", "ovr": "29.3", "bat": "48472", "r_t": "1", "bowl": "56025", "r": "1", "comm": "well outside off and Dilshan turns it to long on too, one more", "x": "253", "y": "311", "o_a": "29.3", "z": "4"}, {"o_u": "29.04", "ovr": "29.4", "bat": "50710", "r_t": "0", "bowl": "56025", "r": "0", "comm": "bit of room outside off, Sanga cuts it late but can't clear point", "x": "244", "y": "166", "o_a": "29.4", "z": "3"}, {"o_u": "29.05", "ovr": "29.5", "bat": "50710", "r_t": "4", "bowl": "56025", "r": "4", "comm": "slower and well outside off, oh that's sloppy fielding! Sanga punched it off the back foot straight to cover and that went through Anamul", "x": "341", "y": "253", "o_a": "29.5", "z": "3"}, {"o_u": "29.06", "ovr": "29.6", "bat": "50710", "r_t": "0", "bowl": "56025", "r": "0", "comm": "fuller outside off and steered to point now", "x": "241", "y": "158", "o_a": "29.6", "z": "2"}, {"o_u": "30.01", "ovr": "30.1", "bat": "48472", "r_t": "4", "bowl": "538506", "r": "4", "comm": "back of length well outside off, Dilshan sees the room and taps it late in the air, fine enough to clear third man for four. Clever shot", "x": "132", "y": "12", "o_a": "30.1", "z": "8"}, {"o_u": "30.02", "ovr": "30.2", "bat": "48472", "r_t": "1", "bowl": "538506", "r": "1", "comm": "fullish on off, driven down to long on for one", "x": "231", "y": "231", "o_a": "30.2", "z": "4"}, {"o_u": "30.03", "ovr": "30.3", "bat": "50710", "r_t": "1", "bowl": "538506", "r": "1", "comm": "on length on middle and leg, steered off the back foot to deep midwicket", "x": "77", "y": "189", "o_a": "30.3", "z": "6"}, {"o_u": "30.04", "ovr": "30.4", "bat": "48472", "r_t": "0", "bowl": "538506", "r": "0", "comm": "bangs in a bouncer and it goes through to the keeper", "x": "0", "y": "0", "o_a": "30.4", "z": "0"}, {"o_u": "30.05", "ovr": "30.5", "bat": "48472", "r_t": "1", "bowl": "538506", "r": "1", "comm": "back of length outside off, cuts it late off the bottom edge to third man", "x": "133", "y": "66", "o_a": "30.5", "z": "8"}, {"o_u": "30.06", "ovr": "30.6", "bat": "50710", "r_t": "0", "bowl": "538506", "r": "0", "comm": "bouncer just around leg stump, Sanga ducks under it", "x": "0", "y": "0", "o_a": "30.6", "z": "0"}, {"o_u": "31.01", "ovr": "31.1", "bat": "48472", "r_t": "0", "bowl": "56025", "r": "0", "comm": "fullish outside off, driven to point off the back foot", "x": "112", "y": "187", "o_a": "31.1", "z": "6"}, {"o_u": "31.02", "ovr": "31.2", "bat": "48472", "r_t": "4", "bowl": "56025", "r": "4", "comm": "shorter outside off, Dilshan gets time and punches it off the back foot to clear cover point now, and gets four", "x": "13", "y": "222", "o_a": "31.2", "z": "6"}, {"o_u": "31.03", "ovr": "31.3", "bat": "48472", "r_t": "1", "bowl": "56025", "r": "1", "comm": "slower through the air, flight and turn, Dilshan helps it down to long on", "x": "282", "y": "283", "o_a": "31.3", "z": "4"}, {"o_u": "31.04", "ovr": "31.4", "bat": "50710", "r_t": "1", "bowl": "56025", "r": "1", "comm": "length delivery on middle, pushed down to long and gives the strike back to Dilshan", "x": "112", "y": "295", "o_a": "31.4", "z": "5"}, {"o_u": "31.05", "ovr": "31.5", "bat": "48472", "r_t": "1", "bowl": "56025", "r": "1", "comm": "flighted but around leg now, steered to deep backward square for one", "x": "267", "y": "150", "o_a": "31.5", "z": "2"}, {"o_u": "31.06", "ovr": "31.6", "bat": "50710", "r_t": "1", "bowl": "56025", "r": "1", "comm": "comes down the track and tucks the ball to deep midwicket for one", "x": "63", "y": "200", "o_a": "31.6", "z": "6"}, {"o_u": "32.01", "ovr": "32.1", "bat": "50710", "r_t": "0", "bowl": "538506", "r": "0", "comm": "on a length, on off, pushed to cover", "x": "241", "y": "185", "o_a": "32.1", "z": "3"}, {"o_u": "32.02", "ovr": "32.2", "bat": "50710", "r_t": "0", "bowl": "538506", "r": "0", "comm": "stays back to punch this length ball square, but can't beat point", "x": "240", "y": "143", "o_a": "32.2", "z": "2"}, {"o_u": "32.03", "ovr": "32.3", "bat": "50710", "r_t": "1", "bowl": "538506", "r": "1", "comm": "fuller, pushed towards mid-off with soft hands, calls Dilshan through for a quick single", "x": "217", "y": "232", "o_a": "32.3", "z": "4"}, {"o_u": "32.04", "ovr": "32.4", "bat": "48472", "r_t": "1", "bowl": "538506", "r": "1", "comm": "short, wide, cut away to deep cover", "x": "52", "y": "113", "o_a": "32.4", "z": "7"}, {"o_u": "32.05", "ovr": "32.5", "bat": "50710", "r_t": "4", "bowl": "538506", "r": "4", "comm": "full, on off, Sanga has driven it wide of mid-off. All along the ground. He has threaded the gap", "x": "341", "y": "248", "o_a": "32.5", "z": "3"}, {"o_u": "32.06", "ovr": "32.6", "bat": "50710", "r_t": "0", "bowl": "538506", "r": "0", "comm": "<b>dropped</b>. Solid attempt in the follow-through but he has failed to hold on. This has stopped on Sanga, and has lobbed in front of Taskin. He stops in the follow-through and then lunges forward", "x": "162", "y": "192", "o_a": "32.6", "z": "5"}, {"o_u": "33.01", "ovr": "33.1", "bat": "48472", "r_t": "1", "bowl": "56143", "r": "1", "comm": "full, middle and leg, driven to long-off", "x": "88", "y": "286", "o_a": "33.1", "z": "5"}, {"o_u": "33.02", "ovr": "33.2", "bat": "50710", "r_t": "0", "bowl": "56143", "r": "0", "comm": "flat and quick, defended off the back foot", "x": "127", "y": "201", "o_a": "33.2", "z": "6"}, {"o_u": "33.03", "ovr": "33.3", "bat": "50710", "r_t": "1", "bowl": "56143", "r": "1", "comm": "driven down the ground for one", "x": "154", "y": "311", "o_a": "33.3", "z": "5"}, {"o_u": "33.04", "ovr": "33.4", "bat": "48472", "r_t": "1", "bowl": "56143", "r": "1", "comm": "", "x": "87", "y": "281", "o_a": "33.4", "z": "5"}, {"o_u": "33.05", "ovr": "33.5", "bat": "50710", "r_t": "0", "bowl": "56143", "r": "0", "comm": "moves in the line, dabs this fine but can't beat short fine leg", "x": "137", "y": "126", "o_a": "33.5", "z": "7"}, {"o_u": "33.06", "ovr": "33.6", "bat": "50710", "r_t": "4", "bowl": "56143", "r": "4", "comm": "full and wide, he moves across, covers the line and drives it between mid-off and cover", "x": "343", "y": "252", "o_a": "33.6", "z": "3"}, {"o_u": "34.01", "ovr": "34.1", "bat": "48472", "r_t": "0", "bowl": "56007", "r": "0", "comm": "short of a length, outside off, cut straight to point", "x": "123", "y": "137", "o_a": "34.1", "z": "7"}, {"o_u": "34.02", "ovr": "34.2", "bat": "48472", "r_t": "0", "bowl": "56007", "r": "0", "comm": "again short of a length, and again punched straight to point", "x": "125", "y": "139", "o_a": "34.2", "z": "7"}, {"o_u": "34.03", "ovr": "34.3", "bat": "48472", "r_t": "0", "bowl": "56007", "r": "0", "comm": "full, middle and off, drilled to short midwicket. Sanga wants a single, Dilshan doesn't. Words exchanged", "x": "251", "y": "196", "o_a": "34.3", "z": "3"}, {"o_u": "34.04", "ovr": "34.4", "bat": "48472", "r_t": "2", "bowl": "56007", "r": "2", "comm": "short of a length, into the pads, worked away for a couple into the leg side", "x": "272", "y": "74", "o_a": "34.4", "z": "2"}, {"o_u": "34.05", "ovr": "34.5", "bat": "48472", "r_t": "2", "bowl": "56007", "r": "2", "comm": "into the pads again, gets inside the line and works this to fine of fine leg for a couple", "x": "234", "y": "30", "o_a": "34.5", "z": "1"}, {"o_u": "34.06", "ovr": "34.6", "bat": "48472", "r_t": "0", "bowl": "56007", "r": "0", "comm": "short of a length, outside off, and Dilshan finds point for the third time in this over", "x": "130", "y": "133", "o_a": "34.6", "z": "7"}, {"o_u": "35.01", "ovr": "35.1", "bat": "50710", "r_t": "0", "bowl": "56143", "r": "0", "comm": "moves across to a length ball outside off, gets a leading edge towards cover", "x": "237", "y": "187", "o_a": "35.1", "z": "3"}, {"o_u": "35.02", "ovr": "35.2", "bat": "50710", "r_t": "1", "bowl": "56143", "r": "0", "comm": "moves inside the line again, tries to sweep, but misses. Lucky his leg stump is standing", "x": "0", "y": "0", "o_a": "35.2", "z": "0"}, {"o_u": "35.03", "ovr": "35.3", "bat": "48472", "r_t": "1", "bowl": "56143", "r": "1", "comm": "short of a length, punched down the ground for one", "x": "286", "y": "287", "o_a": "35.3", "z": "4"}, {"o_u": "35.04", "ovr": "35.4", "bat": "50710", "r_t": "4", "bowl": "56143", "r": "4", "comm": "down the wicket and slogs this over midwicket for four", "x": "23", "y": "247", "o_a": "35.4", "z": "6"}, {"o_u": "35.05", "ovr": "35.5", "bat": "50710", "r_t": "1", "bowl": "56143", "r": "1", "comm": "swept away, but gets just the one this time", "x": "39", "y": "178", "o_a": "35.5", "z": "6"}, {"o_u": "35.06", "ovr": "35.6", "bat": "48472", "r_t": "0", "bowl": "56143", "r": "0", "comm": "length ball outside off, driven on the up, straight to extra cover, though", "x": "114", "y": "198", "o_a": "35.6", "z": "6"}, {"o_u": "36.01", "ovr": "36.1", "bat": "50710", "r_t": "2", "bowl": "56007", "r": "2", "comm": "clears his front leg and slogs at a length ball, gets a couple wide of deep midwicket", "x": "26", "y": "199", "o_a": "36.1", "z": "6"}, {"o_u": "36.02", "ovr": "36.2", "bat": "50710", "r_t": "1", "bowl": "56007", "r": "1", "comm": "slower short ball, half-pulled to midwicket for one", "x": "72", "y": "193", "o_a": "36.2", "z": "6"}, {"o_u": "36.03", "ovr": "36.3", "bat": "48472", "r_t": "0", "bowl": "56007", "r": "0", "comm": "short of a length, angling in, Dilshan is beaten by one that skids through", "x": "0", "y": "0", "o_a": "36.3", "z": "0"}, {"o_u": "36.04", "ovr": "36.4", "bat": "48472", "r_t": "1", "bowl": "56007", "r": "1", "comm": "full and wide, pushed wide of mid-off for one", "x": "117", "y": "217", "o_a": "36.4", "z": "6"}, {"o_u": "36.05", "ovr": "36.5", "bat": "50710", "r_t": "4", "bowl": "56007", "r": "4", "comm": "wide length ball, Sanga clears the front leg and smashes this straight down the ground for a four back over the bowler's head", "x": "192", "y": "360", "o_a": "36.5", "z": "4"}, {"o_u": "36.06", "ovr": "36.6", "bat": "50710", "r_t": "2", "bowl": "56007", "r": "2", "comm": "nicely played. Short of a length, on off, he opens the face, but is denied a boundary by the diving short third man", "x": "186", "y": "54", "o_a": "36.6", "z": "1"}, {"o_u": "37.01", "ovr": "37.1", "bat": "48472", "r_t": "1", "bowl": "373538", "r": "1", "comm": "punched off the back foot, gets a single to extra cover", "x": "117", "y": "213", "o_a": "37.1", "z": "6"}, {"o_u": "37.02", "ovr": "37.2", "bat": "50710", "r_t": "4", "bowl": "373538", "r": "4", "comm": "half-volley outside off, and even though Sanga is opening up his front leg to every delivery he has managed to drive this through the covers for four", "x": "335", "y": "267", "o_a": "37.2", "z": "3"}, {"o_u": "37.03", "ovr": "37.3", "bat": "50710", "r_t": "1", "bowl": "373538", "r": "1", "comm": "stays back to a shortish ball and pulls it to deep square for one", "x": "54", "y": "116", "o_a": "37.3", "z": "7"}, {"o_u": "37.04", "ovr": "37.4", "bat": "48472", "r_t": "1", "bowl": "373538", "r": "1", "comm": "pitched up on off, doesn't let it turn and drives it to long-off for one", "x": "89", "y": "250", "o_a": "37.4", "z": "6"}, {"o_u": "37.05", "ovr": "37.5", "bat": "50710", "r_t": "0", "bowl": "373538", "r": "0", "comm": "<b>superb delivery</b>. Flipper or a toppie. Pitches within the stumps, skids through and hits him right in front. Sanga has got a bottom edge to save himself here", "x": "197", "y": "185", "o_a": "37.5", "z": "4"}, {"o_u": "37.06", "ovr": "37.6", "bat": "50710", "r_t": "1", "bowl": "373538", "r": "0", "comm": "looks to pull a shortish delivery and is beaten", "x": "138", "y": "122", "o_a": "37.6", "z": "8"}, {"o_u": "38.01", "ovr": "38.1", "bat": "50710", "r_t": "0", "bowl": "56143", "r": "0", "comm": "full toss outside leg, he paddles it, finds short fine, sets off for a run that doesn't exist. Sent back but makes it in time", "x": "146", "y": "109", "o_a": "38.1", "z": "8"}, {"o_u": "38.02", "ovr": "38.2", "bat": "50710", "r_t": "1", "bowl": "56143", "r": "1", "comm": "makes room to drive this to long-on for one", "x": "111", "y": "303", "o_a": "38.2", "z": "5"}, {"o_u": "38.03", "ovr": "38.3", "bat": "48472", "r_t": "1", "bowl": "56143", "r": "1", "comm": "flat delivery, into the pads, worked away for a single to square leg", "x": "297", "y": "175", "o_a": "38.3", "z": "3"}, {"o_u": "38.04", "ovr": "38.4", "bat": "50710", "r_t": "0", "bowl": "56143", "r": "0", "comm": "down the wicket, not to the pitch of it, pushes this to midwicket", "x": "127", "y": "212", "o_a": "38.4", "z": "6"}, {"o_u": "38.05", "ovr": "38.5", "bat": "50710", "r_t": "4", "bowl": "56143", "r": "4", "comm": "gets inside the line of a flat delivery to sweep it square for a four to bring up a fifty in 400th ODI", "x": "51", "y": "58", "o_a": "38.5", "z": "7"}, {"o_u": "38.06", "ovr": "38.6", "bat": "50710", "r_t": "0", "bowl": "56143", "r": "0", "comm": "makes room, Shakib slows it down, and Sanga is beaten", "x": "0", "y": "0", "o_a": "38.6", "z": "0"}, {"o_u": "39.01", "ovr": "39.1", "bat": "48472", "r_t": "0", "bowl": "373538", "r": "0", "comm": "legbreak flighted on middle and leg, hit back to the bowler", "x": "230", "y": "203", "o_a": "39.1", "z": "3"}, {"o_u": "39.02", "ovr": "39.2", "bat": "48472", "r_t": "1", "bowl": "373538", "r": "1", "comm": "flatter, quicker, punched away square, misfielded at cover-point", "x": "44", "y": "186", "o_a": "39.2", "z": "6"}, {"o_u": "39.03", "ovr": "39.3", "bat": "50710", "r_t": "1", "bowl": "373538", "r": "1", "comm": "driven down the ground to long-off for one", "x": "246", "y": "311", "o_a": "39.3", "z": "4"}, {"o_u": "39.04", "ovr": "39.4", "bat": "48472", "r_t": "2", "bowl": "373538", "r": "0", "comm": "wide, big wide down the leg side, Mushfiq too fails to collect it", "x": "0", "y": "0", "o_a": "39.4", "z": "0"}, {"o_u": "39.05", "ovr": "39.4", "bat": "50710", "r_t": "2", "bowl": "373538", "r": "2", "comm": "short, makes room to pull it wide of long-on for a couple", "x": "53", "y": "268", "o_a": "39.4", "z": "6"}, {"o_u": "39.06", "ovr": "39.5", "bat": "50710", "r_t": "0", "bowl": "373538", "r": "0", "comm": "flighted outside leg, swept straight to short fine. He has missed out again", "x": "134", "y": "126", "o_a": "39.5", "z": "7"}, {"o_u": "39.07", "ovr": "39.6", "bat": "50710", "r_t": "1", "bowl": "373538", "r": "1", "comm": "comes down the ground to take this on the full and drive it to long-on", "x": "120", "y": "330", "o_a": "39.6", "z": "5"}, {"o_u": "40.01", "ovr": "40.1", "bat": "50710", "r_t": "3", "bowl": "56143", "r": "3", "comm": "plays the reverse. Takes this from outside what would have been leg and lofts it over point for three", "x": "261", "y": "47", "o_a": "40.1", "z": "1"}, {"o_u": "40.02", "ovr": "40.2", "bat": "48472", "r_t": "0", "bowl": "56143", "r": "0", "comm": "full and slow, middle and leg, defended back to him", "x": "188", "y": "196", "o_a": "40.2", "z": "4"}, {"o_u": "40.03", "ovr": "40.3", "bat": "48472", "r_t": "1", "bowl": "56143", "r": "1", "comm": "short of a length, he rocks back to punch it to deep cover and reach 99", "x": "58", "y": "180", "o_a": "40.3", "z": "6"}, {"o_u": "40.04", "ovr": "40.4", "bat": "50710", "r_t": "1", "bowl": "56143", "r": "1", "comm": "makes room to drive this low fullie down to long-on", "x": "87", "y": "289", "o_a": "40.4", "z": "5"}, {"o_u": "40.05", "ovr": "40.5", "bat": "48472", "r_t": "2", "bowl": "56143", "r": "2", "comm": "the hundred is up through an inside edge. He jumps outside the crease, is beaten in the flight, but gets an inside edge fine of short fine leg. Century No. 21. Looks up at the skies in gratitude. Valuable player", "x": "202", "y": "38", "o_a": "40.5", "z": "1"}, {"o_u": "40.06", "ovr": "40.6", "bat": "48472", "r_t": "0", "bowl": "56143", "r": "0", "comm": "looks to reverse over point but is beaten", "x": "0", "y": "0", "o_a": "40.6", "z": "0"}, {"o_u": "41.01", "ovr": "41.1", "bat": "50710", "r_t": "3", "bowl": "300619", "r": "3", "comm": "<b>another drop</b>. Bangladesh have been fielding poorly. the whole system has broken down. Cut straight to Mominul at point, who has dropped a sitter by international standards. Then he throws at the bowler's end in frustration. The bowler doesn't know a throw is coming, and the long-on has turned his back ton the game. Almost four overthrows a couple of yards to the right of a fielder. Poor stuff", "x": "239", "y": "157", "o_a": "41.1", "z": "2"}, {"o_u": "41.02", "ovr": "41.2", "bat": "48472", "r_t": "4", "bowl": "300619", "r": "4", "comm": "and now that he has reached the hundred, Dilshan becomes more adventurous. Ramps this full ball over short fine leg's head", "x": "246", "y": "16", "o_a": "41.2", "z": "1"}, {"o_u": "41.03", "ovr": "41.3", "bat": "48472", "r_t": "1", "bowl": "300619", "r": "1", "comm": "shapes up for the ramp again, realises the length is not quite right, and he sweeps it square", "x": "312", "y": "106", "o_a": "41.3", "z": "2"}, {"o_u": "41.04", "ovr": "41.4", "bat": "50710", "r_t": "6", "bowl": "300619", "r": "6", "comm": "straight six. At any ground it is a joy, but at MCG there is something extra to it. Makes room to get under a full ball, and sends it sailing back over the bowler's head", "x": "185", "y": "363", "o_a": "41.4", "z": "4"}, {"o_u": "41.05", "ovr": "41.5", "bat": "50710", "r_t": "1", "bowl": "300619", "r": "1", "comm": "this time he opens the face and gets a single", "x": "285", "y": "188", "o_a": "41.5", "z": "3"}, {"o_u": "41.06", "ovr": "41.6", "bat": "48472", "r_t": "0", "bowl": "300619", "r": "0", "comm": "charges at him to try to slash him over cover, but is beaten by a slower ball", "x": "0", "y": "0", "o_a": "41.6", "z": "0"}, {"o_u": "42.01", "ovr": "42.1", "bat": "50710", "r_t": "1", "bowl": "538506", "r": "1", "comm": "starts with a low full toss, drilled down to long-on for one", "x": "97", "y": "304", "o_a": "42.1", "z": "5"}, {"o_u": "42.02", "ovr": "42.2", "bat": "48472", "r_t": "1", "bowl": "538506", "r": "1", "comm": "another low full toss, hit straight to extra cover, Dilshan is halfway down the wicket, but <b>Mushfiqur has not taken one step</b> towards the stumps. This is poor keeping. And the fielder misses with the direct hit. Really pedestrian from Bangladesh", "x": "108", "y": "186", "o_a": "42.2", "z": "6"}, {"o_u": "42.03", "ovr": "42.3", "bat": "50710", "r_t": "1", "bowl": "538506", "r": "1", "comm": "dug out for a single", "x": "112", "y": "189", "o_a": "42.3", "z": "6"}, {"o_u": "42.04", "ovr": "42.4", "bat": "48472", "r_t": "2", "bowl": "538506", "r": "2", "comm": "low full toss, driven down the ground, but can't beat mid-off", "x": "126", "y": "278", "o_a": "42.4", "z": "5"}, {"o_u": "42.05", "ovr": "42.5", "bat": "48472", "r_t": "1", "bowl": "538506", "r": "1", "comm": "full, just outside off, driven straight to extra cover", "x": "98", "y": "199", "o_a": "42.5", "z": "6"}, {"o_u": "42.06", "ovr": "42.6", "bat": "50710", "r_t": "2", "bowl": "538506", "r": "2", "comm": "which is why Sanga tries to move inside the line and ramp this, but the ball is a touch too wide, and he gets just a couple wide of short fine leg", "x": "87", "y": "80", "o_a": "42.6", "z": "7"}, {"o_u": "43.01", "ovr": "43.1", "bat": "48472", "r_t": "0", "bowl": "56025", "r": "0", "comm": "looks to reverse-hit this one, and is beaten what would have been outside leg", "x": "0", "y": "0", "o_a": "43.1", "z": "0"}, {"o_u": "43.02", "ovr": "43.2", "bat": "48472", "r_t": "1", "bowl": "56025", "r": "0", "comm": "Dilshan tries another reverse hit, and Mahmudullah slows it down this time to beat him outside off. Gets a leg-bye", "x": "214", "y": "117", "o_a": "43.2", "z": "1"}, {"o_u": "43.03", "ovr": "43.3", "bat": "50710", "r_t": "4", "bowl": "56025", "r": "4", "comm": "short, pulled away between long-on and deep midwicket. He has the field back on the leg side, but can't afford to drop it 11 yards down the wicket", "x": "36", "y": "282", "o_a": "43.3", "z": "6"}, {"o_u": "43.04", "ovr": "43.4", "bat": "50710", "r_t": "1", "bowl": "56025", "r": "1", "comm": "down the wicket to drive this to long-off for one", "x": "281", "y": "278", "o_a": "43.4", "z": "4"}, {"o_u": "43.05", "ovr": "43.5", "bat": "48472", "r_t": "1", "bowl": "56025", "r": "1", "comm": "driven down to long-on for one", "x": "252", "y": "306", "o_a": "43.5", "z": "4"}, {"o_u": "43.06", "ovr": "43.6", "bat": "50710", "r_t": "4", "bowl": "56025", "r": "4", "comm": "Sanga is on fire here. He gets outside off, in line with an offbreak, and then sweeps this over square leg for four more", "x": "28", "y": "96", "o_a": "43.6", "z": "7"}, {"o_u": "44.01", "ovr": "44.1", "bat": "48472", "r_t": "4", "bowl": "538506", "r": "4", "comm": "Dilshan gets the length ball he has been looking for and clears cover with ease. Poor delivery with the field on the off side up in the circle. A length ball outside off", "x": "14", "y": "229", "o_a": "44.1", "z": "6"}, {"o_u": "44.02", "ovr": "44.2", "bat": "48472", "r_t": "0", "bowl": "538506", "r": "0", "comm": "slightly short of a length, still an ordinary delivery, but Dilshan is beaten by the pace this time", "x": "0", "y": "0", "o_a": "44.2", "z": "0"}, {"o_u": "44.03", "ovr": "44.3", "bat": "48472", "r_t": "0", "bowl": "538506", "r": "0", "comm": "slower ball, Dilshan doesn't read it, and he cramps him up with the middle-and-leg line. Gets a dot out of this", "x": "0", "y": "0", "o_a": "44.3", "z": "0"}, {"o_u": "44.04", "ovr": "44.4", "bat": "48472", "r_t": "4", "bowl": "538506", "r": "4", "comm": "this time Dilshan makes room and drills this full ball between the bowler and mid-off. Decent delivery. Full to cramp him up with a strong leg-side field. Dilshan plays it well by making room and timing it superbly", "x": "115", "y": "345", "o_a": "44.4", "z": "5"}, {"o_u": "44.05", "ovr": "44.5", "bat": "48472", "r_t": "4", "bowl": "538506", "r": "4", "comm": "another slower ball, this time Dilshan has picked it, and he swings it square of deep square leg for four more", "x": "311", "y": "65", "o_a": "44.5", "z": "2"}, {"o_u": "44.06", "ovr": "44.6", "bat": "48472", "r_t": "4", "bowl": "538506", "r": "4", "comm": "misses the yorker. This is a low full toss. The idea is right, the execution isn't. He has swung hard at it, and has cleared midwicket with it. Deep square leg can't get around in time. Four fours in the over", "x": "351", "y": "221", "o_a": "44.6", "z": "3"}, {"o_u": "45.01", "ovr": "45.1", "bat": "50710", "r_t": "0", "bowl": "56025", "r": "0", "comm": "slower through the air, slightly short of driving length, beats the bottom edge as Sanga looks to go square on the off side", "x": "0", "y": "0", "o_a": "45.1", "z": "0"}, {"o_u": "45.02", "ovr": "45.2", "bat": "50710", "r_t": "4", "bowl": "56025", "r": "4", "comm": "that's a Sanga special. This is full and wide, flat too, and he plays the trademark extra-cover drive, going inside-out over cover", "x": "355", "y": "173", "o_a": "45.2", "z": "3"}, {"o_u": "45.03", "ovr": "45.3", "bat": "50710", "r_t": "2", "bowl": "56025", "r": "2", "comm": "slower through the air, driven square of deep midwicket for two", "x": "31", "y": "197", "o_a": "45.3", "z": "6"}, {"o_u": "45.04", "ovr": "45.4", "bat": "50710", "r_t": "1", "bowl": "56025", "r": "1", "comm": "down the wicket to drive this to long-on for one", "x": "104", "y": "289", "o_a": "45.4", "z": "5"}, {"o_u": "45.05", "ovr": "45.5", "bat": "48472", "r_t": "1", "bowl": "56025", "r": "0", "comm": "looks for the reverse again, and is beaten by a long distance. Bangladesh are asking for an lbw, but Aleem Dar has called byes. And rightly so", "x": "0", "y": "0", "o_a": "45.5", "z": "0"}, {"o_u": "45.06", "ovr": "45.6", "bat": "50710", "r_t": "0", "bowl": "56025", "r": "0", "comm": "looks to sweep this from wide outside off, hit on the pad as he is early into the shot", "x": "0", "y": "0", "o_a": "45.6", "z": "0"}, {"o_u": "46.01", "ovr": "46.1", "bat": "48472", "r_t": "4", "bowl": "56007", "r": "4", "comm": "he starts short and wide with third man and point inside the circle. Ordinary. Cut away for an easy four", "x": "61", "y": "55", "o_a": "46.1", "z": "7"}, {"o_u": "46.02", "ovr": "46.2", "bat": "48472", "r_t": "4", "bowl": "56007", "r": "4", "comm": "full and wide with the off-side field up in the circle. Just don't get this thinking. Drilled past extra cover for four more", "x": "11", "y": "208", "o_a": "46.2", "z": "6"}, {"o_u": "46.03", "ovr": "46.3", "bat": "48472", "r_t": "1", "bowl": "56007", "r": "1", "comm": "slower yorker, Dilshan is early into an attempted sweep. Gets an inside edge onto the pad", "x": "127", "y": "142", "o_a": "46.3", "z": "7"}, {"o_u": "46.04", "ovr": "46.4", "bat": "50710", "r_t": "4", "bowl": "56007", "r": "4", "comm": "lovely shot. Can't do much against such batting. He makes room, gets under a length ball and chips him over cover. Superb timing too", "x": "355", "y": "205", "o_a": "46.4", "z": "3"}, {"o_u": "46.05", "ovr": "46.5", "bat": "50710", "r_t": "1", "bowl": "56007", "r": "1", "comm": "driven into the off side again, but this time they have placed a deep cover", "x": "305", "y": "185", "o_a": "46.5", "z": "3"}, {"o_u": "46.06", "ovr": "46.6", "bat": "48472", "r_t": "0", "bowl": "56007", "r": "0", "comm": "again on a length and outside off with the off-side field up. Lucky that Dilshan has found extra cover with this shot", "x": "107", "y": "203", "o_a": "46.6", "z": "6"}, {"o_u": "47.01", "ovr": "47.1", "bat": "50710", "r_t": "1", "bowl": "56143", "r": "1", "comm": "down the wicket to work this into the leg side for a single", "x": "63", "y": "190", "o_a": "47.1", "z": "6"}, {"o_u": "47.02", "ovr": "47.2", "bat": "48472", "r_t": "4", "bowl": "56143", "r": "4", "comm": "full and flat, Dilshan sweeps, gets a thick inside edge past short fine leg. That brings up the 300", "x": "307", "y": "58", "o_a": "47.2", "z": "2"}, {"o_u": "47.03", "ovr": "47.3", "bat": "48472", "r_t": "0", "bowl": "56143", "r": "0", "comm": "full and wide, well bowled. Beats the outside edge. Just inside the tram lines", "x": "0", "y": "0", "o_a": "47.3", "z": "0"}, {"o_u": "47.04", "ovr": "47.4", "bat": "48472", "r_t": "4", "bowl": "56143", "r": "4", "comm": "tries the full and wide ball again, but Dilshan this time reverses his stance and sends it between point and short third man for four. This is a switch hit", "x": "36", "y": "85", "o_a": "47.4", "z": "7"}, {"o_u": "47.05", "ovr": "47.5", "bat": "48472", "r_t": "0", "bowl": "56143", "r": "0", "comm": "tries another reverse shot, but he has slowed it down and beaten Dilshan outside off", "x": "0", "y": "0", "o_a": "47.5", "z": "0"}, {"o_u": "47.06", "ovr": "47.6", "bat": "48472", "r_t": "4", "bowl": "56143", "r": "4", "comm": "and a slugged boundary to end the over. This is a length ball, and he has hoicked it past square leg for four more", "x": "301", "y": "51", "o_a": "47.6", "z": "2"}, {"o_u": "48.01", "ovr": "48.1", "bat": "50710", "r_t": "1", "bowl": "300619", "r": "1", "comm": "low full toss, Sanga gets a single to long-off", "x": "268", "y": "236", "o_a": "48.1", "z": "3"}, {"o_u": "48.02", "ovr": "48.2", "bat": "48472", "r_t": "1", "bowl": "300619", "r": "1", "comm": "nice yorker, swinging in. Dilshan digs it out for a single", "x": "160", "y": "175", "o_a": "48.2", "z": "6"}, {"o_u": "48.03", "ovr": "48.3", "bat": "50710", "r_t": "1", "bowl": "300619", "r": "1", "comm": "Rubel stays full and straight, he is driven but along the ground and just for a single to deep cover", "x": "323", "y": "183", "o_a": "48.3", "z": "3"}, {"o_u": "48.04", "ovr": "48.4", "bat": "48472", "r_t": "4", "bowl": "300619", "r": "4", "comm": "misses the yorker by inches. Dilshan goes deep into the crease and lofts him over midwicket for four. His third 150 in ODIs", "x": "339", "y": "250", "o_a": "48.4", "z": "3"}, {"o_u": "48.05", "ovr": "48.5", "bat": "48472", "r_t": "3", "bowl": "300619", "r": "3", "comm": "wide yorker, he has squeezed it out between point and short third man, and they come back for the third too", "x": "70", "y": "71", "o_a": "48.5", "z": "7"}, {"o_u": "48.06", "ovr": "48.6", "bat": "50710", "r_t": "1", "bowl": "300619", "r": "1", "comm": "Rubel stays full and straight to Sanga, who digs it out for a single to mid-off. He is 99 and has the strike", "x": "243", "y": "218", "o_a": "48.6", "z": "3"}, {"o_u": "49.01", "ovr": "49.1", "bat": "50710", "r_t": "1", "bowl": "538506", "r": "1", "comm": "there it is. Sanga's fastest hundred. In his 400th ODI. Driven hard down to long-off for the single. 35,000 at MCG are on their feet. Sanga is congratulated by Dilshan, and they go back to business", "x": "265", "y": "308", "o_a": "49.1", "z": "4"}, {"o_u": "49.02", "ovr": "49.2", "bat": "48472", "r_t": "4", "bowl": "538506", "r": "4", "comm": "low full toss into the pads, and he has placed it between fine leg and deep square leg for another four", "x": "334", "y": "89", "o_a": "49.2", "z": "2"}, {"o_u": "49.03", "ovr": "49.3", "bat": "48472", "r_t": "1", "bowl": "538506", "r": "0", "comm": "short, too short, that's a big bouncer. Too high", "x": "0", "y": "0", "o_a": "49.3", "z": "0"}, {"o_u": "49.04", "ovr": "49.3", "bat": "48472", "r_t": "1", "bowl": "538506", "r": "1", "comm": "short, pulled away to square leg for a single. That's Dilshan's highest score in ODIs", "x": "235", "y": "147", "o_a": "49.3", "z": "2"}, {"o_u": "49.05", "ovr": "49.4", "bat": "50710", "r_t": "0", "bowl": "538506", "r": "0", "comm": "looks to move inside the line to ramp this length ball over fine leg, and is beaten clean by a full ball outside off", "x": "0", "y": "0", "o_a": "49.4", "z": "0"}, {"o_u": "49.06", "ovr": "49.5", "bat": "50710", "r_t": "4", "bowl": "538506", "r": "4", "comm": "full, on the pads, he stays deep in the crease to get under it, and he has picked the gap between long-on and deep midwicket for four more", "x": "30", "y": "264", "o_a": "49.5", "z": "6"}, {"o_u": "49.07", "ovr": "49.6", "bat": "50710", "r_t": "1", "bowl": "538506", "r": "1", "comm": "low full toss, driven to deep cover for one to end the innings", "x": "329", "y": "199", "o_a": "49.6", "z": "3"}]}